river_torch/__init__.py
river_torch/__version__.py
river_torch/base.py
river_torch/anomaly/__init__.py
river_torch/anomaly/ae.py
river_torch/anomaly/probability_weighted_ae.py
river_torch/anomaly/rolling_ae.py
river_torch/anomaly/scaler.py
river_torch/classification/__init__.py
river_torch/classification/classifier.py
river_torch/classification/rolling_classifier.py
river_torch/regression/__init__.py
river_torch/regression/regressor.py
river_torch/regression/rolling_regressor.py
river_torch/utils/__init__.py
river_torch/utils/estimator_checks.py
river_torch/utils/hooks.py
river_torch/utils/params.py
river_torch/utils/tensor_conversion.py
river_torch/utils/test_estimators.py
river_torch/utils/test_tensor_conversion.py
river_torch-0.1.2.dist-info/LICENSE
river_torch-0.1.2.dist-info/METADATA
river_torch-0.1.2.dist-info/WHEEL
river_torch-0.1.2.dist-info/top_level.txt
river_torch-0.1.2.dist-info/RECORD
